jadio_package_creator/__init__.py
jadio_package_creator/cli/__init__.py
jadio_package_creator/cli/ai.py
jadio_package_creator/cli/cli.py
jadio_package_creator/cli/clicommands.json
jadio_package_creator/cli/config.py
jadio_package_creator/cli/create.py
jadio_package_creator/cli/init.py
jadio_package_creator/cli/main.py
jadio_package_creator-0.0.6.dist-info/METADATA
jadio_package_creator-0.0.6.dist-info/WHEEL
jadio_package_creator-0.0.6.dist-info/entry_points.txt
jadio_package_creator-0.0.6.dist-info/licenses/license.md
jadio_package_creator-0.0.6.dist-info/RECORD
