Metadata-Version: 2.4
Name: jadio-package-creator
Version: 0.0.6
Summary: Package creator module for Jadio framework
Project-URL: Homepage, https://pypi.org/project/jadio-package-creator/0.0.1/
Project-URL: Repository, https://github.com/JaxxyJadio/jadio-package-creator
License-Expression: MIT
License-File: license.md
Keywords: framework,jadio,jpc,package-creator
Classifier: Development Status :: 3 - Alpha
Classifier: Intended Audience :: Developers
Classifier: License :: OSI Approved :: MIT License
Classifier: Programming Language :: Python :: 3
Classifier: Programming Language :: Python :: 3.8
Classifier: Programming Language :: Python :: 3.9
Classifier: Programming Language :: Python :: 3.10
Classifier: Programming Language :: Python :: 3.11
Classifier: Programming Language :: Python :: 3.12
Requires-Python: >=3.8
Requires-Dist: jadio>=0.0.2
